<?xml version="1.0" encoding="UTF-8"?>
<MetaDataObject xmlns="http://v8.1c.ru/8.3/MDClasses" xmlns:app="http://v8.1c.ru/8.2/managed-application/core" xmlns:cfg="http://v8.1c.ru/8.1/data/enterprise/current-config" xmlns:cmi="http://v8.1c.ru/8.2/managed-application/cmi" xmlns:ent="http://v8.1c.ru/8.1/data/enterprise" xmlns:lf="http://v8.1c.ru/8.2/managed-application/logform" xmlns:style="http://v8.1c.ru/8.1/data/ui/style" xmlns:sys="http://v8.1c.ru/8.1/data/ui/fonts/system" xmlns:v8="http://v8.1c.ru/8.1/data/core" xmlns:v8ui="http://v8.1c.ru/8.1/data/ui" xmlns:web="http://v8.1c.ru/8.1/data/ui/colors/web" xmlns:win="http://v8.1c.ru/8.1/data/ui/colors/windows" xmlns:xen="http://v8.1c.ru/8.3/xcf/enums" xmlns:xpr="http://v8.1c.ru/8.3/xcf/predef" xmlns:xr="http://v8.1c.ru/8.3/xcf/readable" xmlns:xs="http://www.w3.org/2001/XMLSchema" xmlns:xsi="http://www.w3.org/2001/XMLSchema-instance" version="2.4">
	<Constant uuid="e22f7f06-5c91-4a67-8e25-29c6a3183bf7">
		<InternalInfo>
			<xr:GeneratedType name="ConstantManager.РазрешенаРаботаСНовостями" category="Manager">
				<xr:TypeId>78b52dc9-c5e7-4fc1-965c-7b674abe5add</xr:TypeId>
				<xr:ValueId>e6a3f641-9d13-4eab-9a6d-911141f78681</xr:ValueId>
			</xr:GeneratedType>
			<xr:GeneratedType name="ConstantValueManager.РазрешенаРаботаСНовостями" category="ValueManager">
				<xr:TypeId>0c4992cb-87b2-4fe7-90c0-3b2950169d04</xr:TypeId>
				<xr:ValueId>5f096de8-0371-41f4-86be-7fd2be431f76</xr:ValueId>
			</xr:GeneratedType>
		</InternalInfo>
		<Properties>
			<Name>РазрешенаРаботаСНовостями</Name>
			<ObjectBelonging>Adopted</ObjectBelonging>
			<Type>
				<v8:Type>xs:boolean</v8:Type>
			</Type>
		</Properties>
	</Constant>
</MetaDataObject>